{
	"ambient_color" : 
	[
		0.67000000000000004,
		0.66000000000000003,
		0.57999999999999996
	],
	"camera_direction" : 
	[
		0.0,
		0.0,
		-1.0
	],
	"camera_position" : 
	[
		0.0,
		10.0,
		86.0
	],
	"rendering_objects" : 
	[
		{
			"instanced" : true,
			"instances_transforms" : 
			[
				{
					"transform" : 
					[
						2.2947187423706055,
						0.0,
						0.0,
						-18.865562438964844,
						0.0,
						-1.0031767772034073e-07,
						-2.2950010299682617,
						0.0,
						0.0,
						2.2950010299682617,
						-1.0031767772034073e-07,
						-6.2784233093261719,
						0.0,
						0.0,
						0.0,
						1.0
					]
				},
				{
					"transform" : 
					[
						1.6998298168182373,
						0.0,
						0.0,
						-33.0,
						0.0,
						-7.4309362219082686e-08,
						-1.7000000476837158,
						0.0,
						0.0,
						1.7000000476837158,
						-7.4309362219082686e-08,
						-29.536291122436523,
						0.0,
						0.0,
						0.0,
						1.0
					]
				},
				{
					"transform" : 
					[
						0.99993902444839478,
						0.0,
						0.0,
						-34.9249267578125,
						0.0,
						-4.3711388286737929e-08,
						-1.0,
						0.0,
						0.0,
						1.0,
						-4.3711388286737929e-08,
						32.064674377441406,
						0.0,
						0.0,
						0.0,
						1.0
					]
				},
				{
					"transform" : 
					[
						1.4999762773513794,
						0.0,
						0.0,
						26.0,
						0.0,
						-6.5567078877393214e-08,
						-1.5,
						0.0,
						0.0,
						1.5,
						-6.5567078877393214e-08,
						22.0,
						0.0,
						0.0,
						0.0,
						1.0
					]
				},
				{
					"transform" : 
					[
						1.8998267650604248,
						0.0,
						0.0,
						6.2980918884277344,
						0.0,
						-8.3051638455344801e-08,
						-1.8999999761581421,
						0.0,
						0.0,
						1.8999999761581421,
						-8.3051638455344801e-08,
						-18.0,
						0.0,
						0.0,
						0.0,
						1.0
					]
				}
			],
			"materials" : 
			[
				{
					"effect" : "content\\effects\\DepthMap.fx",
					"name" : "DepthMapMaterial",
					"technique" : "create_depthmap_w_render_target_instanced"
				},
				{
					"effect" : "content\\effects\\DeferredPrepass.fx",
					"name" : "DeferredMaterial",
					"technique" : "deferred_instanced"
				},
				{
					"effect" : "content\\effects\\StandardLighting.fx",
					"name" : "StandardLightingMaterial",
					"technique" : "standard_lighting_pbr_instancing"
				}
			],
			"model_path" : "content\\models\\vegetation\\trees\\acer\\tree_acer_middle2_low.fbx",
			"name" : "Acer Tree",
			"transform" : 
			[
				0.99993902444839478,
				0.0,
				0.0,
				-34.9249267578125,
				0.0,
				-4.3711388286737929e-08,
				-1.0,
				0.0,
				0.0,
				1.0,
				-4.3711388286737929e-08,
				32.064674377441406,
				0.0,
				0.0,
				0.0,
				1.0
			]
		},
		{
			"instanced" : false,
			"materials" : 
			[
				{
					"effect" : "content\\effects\\DepthMap.fx",
					"name" : "DepthMapMaterial",
					"technique" : "create_depthmap_w_render_target"
				},
				{
					"effect" : "content\\effects\\DeferredPrepass.fx",
					"name" : "DeferredMaterial",
					"technique" : "deferred"
				},
				{
					"effect" : "content\\effects\\StandardLighting.fx",
					"name" : "StandardLightingMaterial",
					"technique" : "standard_lighting_pbr"
				}
			],
			"model_path" : "content\\models\\default_plane\\default_plane.fbx",
			"name" : "Ground Plane",
			"transform" : 
			[
				1.0,
				0.0,
				0.0,
				0.0,
				0.0,
				1.0,
				0.0,
				0.0,
				0.0,
				0.0,
				1.0,
				0.0,
				0.0,
				0.0,
				0.0,
				1.0
			]
		},
		{
			"instanced" : false,
			"materials" : 
			[
				{
					"effect" : "content\\effects\\DepthMap.fx",
					"name" : "DepthMapMaterial",
					"technique" : "create_depthmap_w_render_target"
				},
				{
					"effect" : "content\\effects\\DeferredPrepass.fx",
					"name" : "DeferredMaterial",
					"technique" : "deferred"
				},
				{
					"effect" : "content\\effects\\StandardLighting.fx",
					"name" : "StandardLightingMaterial",
					"technique" : "standard_lighting_pbr"
				}
			],
			"model_path" : "content\\models\\sphere.fbx",
			"name" : "Test sphere 1",
			"transform" : 
			[
				0.58420002460479736,
				0.0,
				0.0,
				-27.674488067626953,
				0.0,
				0.58420002460479736,
				0.0,
				7.1017065048217773,
				0.0,
				0.0,
				0.58420002460479736,
				14.758570671081543,
				0.0,
				0.0,
				0.0,
				1.0
			]
		},
		{
			"instanced" : false,
			"materials" : 
			[
				{
					"effect" : "content\\effects\\DepthMap.fx",
					"name" : "DepthMapMaterial",
					"technique" : "create_depthmap_w_render_target"
				},
				{
					"effect" : "content\\effects\\DeferredPrepass.fx",
					"name" : "DeferredMaterial",
					"technique" : "deferred"
				},
				{
					"effect" : "content\\effects\\StandardLighting.fx",
					"name" : "StandardLightingMaterial",
					"technique" : "standard_lighting_pbr"
				}
			],
			"model_path" : "content\\models\\sphere.fbx",
			"name" : "Test sphere 2",
			"transform" : 
			[
				1.0049999952316284,
				0.0,
				0.0,
				22.884361267089844,
				0.0,
				1.0049999952316284,
				0.0,
				-0.28352832794189453,
				0.0,
				0.0,
				1.0049999952316284,
				-14.831348419189453,
				0.0,
				0.0,
				0.0,
				1.0
			]
		},
		{
			"instanced" : false,
			"materials" : 
			[
				{
					"effect" : "content\\effects\\DepthMap.fx",
					"name" : "DepthMapMaterial",
					"technique" : "create_depthmap_w_render_target"
				},
				{
					"effect" : "content\\effects\\DeferredPrepass.fx",
					"name" : "DeferredMaterial",
					"technique" : "deferred"
				},
				{
					"effect" : "content\\effects\\StandardLighting.fx",
					"name" : "StandardLightingMaterial",
					"technique" : "standard_lighting_pbr"
				}
			],
			"model_path" : "content\\models\\shaderball.fbx",
			"name" : "Test sphere 3",
			"transform" : 
			[
				0.92000007629394531,
				0.0,
				0.0,
				-2.8697218894958496,
				0.0,
				0.92000007629394531,
				0.0,
				-0.063421785831451416,
				0.0,
				0.0,
				0.92000007629394531,
				0.0,
				0.0,
				0.0,
				0.0,
				1.0
			]
		}
	],
	"skybox_path" : "content\\textures\\skyboxes\\Sky_2\\textureEnv.dds",
	"sun_color" : 
	[
		1.0,
		0.94999999999999996,
		0.85999999999999999
	],
	"sun_direction" : []
}